pymodaq_plugins_piezoconcept/__init__.py
pymodaq_plugins_piezoconcept/utils.py
pymodaq_plugins_piezoconcept/daq_move_plugins/__init__.py
pymodaq_plugins_piezoconcept/daq_move_plugins/daq_move_PiezoConcept.py
pymodaq_plugins_piezoconcept/daq_move_plugins/daq_move_PiezoConceptPI.py
pymodaq_plugins_piezoconcept/daq_viewer_plugins/__init__.py
pymodaq_plugins_piezoconcept/daq_viewer_plugins/plugins_0D/__init__.py
pymodaq_plugins_piezoconcept/daq_viewer_plugins/plugins_1D/__init__.py
pymodaq_plugins_piezoconcept/daq_viewer_plugins/plugins_2D/__init__.py
pymodaq_plugins_piezoconcept/daq_viewer_plugins/plugins_ND/__init__.py
pymodaq_plugins_piezoconcept/hardware/__init__.py
pymodaq_plugins_piezoconcept/hardware/piezoconcept/__init__.py
pymodaq_plugins_piezoconcept/hardware/piezoconcept/piezoconcept.py
pymodaq_plugins_piezoconcept/resources/__init__.py
pymodaq_plugins_piezoconcept/resources/config_template.toml
pymodaq_plugins_piezoconcept-5.0.2.dist-info/METADATA
pymodaq_plugins_piezoconcept-5.0.2.dist-info/WHEEL
pymodaq_plugins_piezoconcept-5.0.2.dist-info/entry_points.txt
pymodaq_plugins_piezoconcept-5.0.2.dist-info/licenses/LICENSE
pymodaq_plugins_piezoconcept-5.0.2.dist-info/RECORD
